{
  "project_info": {
    "project_number": "212511382840",
    "project_id": "NourishBite-4be09",
    "storage_bucket": "NourishBite-4be09.appspot.com"
  },
  "client": [
    {
      "client_info": {
        "mobilesdk_app_id": "1:212511382840:android:f83670c091f677d20ab5cd",
        "android_client_info": {
          "package_name": "com.parallelsapplication.app"
        }
      },
      "oauth_client": [],
      "api_key": [
        {
          "current_key": "AIzaSyBvSPfXdZH9XmAUZtjGhDr2-zCdYHy2-yM"
        }
      ],
      "services": {
        "appinvite_service": {
          "other_platform_oauth_client": []
        }
      }
    }
  ],
  "configuration_version": "1"
}